{
  "M20170711014017016676156": {
    "kdtId": 358764,
    "yzUid": 4716328,
    "orderNo": "M20170711014017016676156",
    "fromSource": 3,
    "orderState": 30,
    "orderType": 1,
    "cashierId": 4693602,
    "remark": "",
    "buyerMemo": "",
    "reserveOrderId": "",
    "reserveOrderNo": "",
    "billOrderNo": "E20170711014017080800001",
    "billOrderId": "1391727736149508097",
    "finishTime": 0,
    "billTime": 1499708417,
    "reserveTime": 0,
    "guestName": "",
    "guestGender": 0,
    "createTime": 1499708417,
    "updateTime": 1499708417,
    "billOrderPaid": false,
    "billOrderRefund": false
  },
  "M20170802202555094513055": {
    "kdtId": 358764,
    "yzUid": 4693602,
    "orderNo": "M20170802202555094513055",
    "fromSource": 3,
    "orderState": 30,
    "orderType": 1,
    "cashierId": 0,
    "remark": "",
    "buyerMemo": "",
    "reserveOrderId": "",
    "reserveOrderNo": "",
    "billOrderNo": "E20170802202556061000001",
    "billOrderId": "1395954711861919745",
    "finishTime": 0,
    "billTime": 1501676756,
    "reserveTime": 0,
    "guestName": "",
    "guestGender": 0,
    "createTime": 1501676756,
    "updateTime": 1501676756,
    "billOrderPaid": false,
    "billOrderRefund": false
  },
  "M20170802192503071485565": {
    "kdtId": 358764,
    "yzUid": 4693602,
    "orderNo": "M20170802192503071485565",
    "fromSource": 3,
    "orderState": 30,
    "orderType": 1,
    "cashierId": 0,
    "remark": "",
    "buyerMemo": "",
    "reserveOrderId": "",
    "reserveOrderNo": "",
    "billOrderNo": "E20170802192503061000001",
    "billOrderId": "1395946867104153601",
    "finishTime": 0,
    "billTime": 1501673103,
    "reserveTime": 0,
    "guestName": "",
    "guestGender": 0,
    "createTime": 1501673103,
    "updateTime": 1501673103,
    "billOrderPaid": false,
    "billOrderRefund": false
  },
  "M20170802203319068950823": {
    "kdtId": 358764,
    "yzUid": 4693602,
    "orderNo": "M20170802203319068950823",
    "fromSource": 3,
    "orderState": 30,
    "orderType": 1,
    "cashierId": 0,
    "remark": "",
    "buyerMemo": "",
    "reserveOrderId": "",
    "reserveOrderNo": "",
    "billOrderNo": "E20170802203319061000001",
    "billOrderId": "1395955663197175809",
    "finishTime": 0,
    "billTime": 1501677199,
    "reserveTime": 0,
    "guestName": "",
    "guestGender": 0,
    "createTime": 1501677199,
    "updateTime": 1501677199,
    "billOrderPaid": false,
    "billOrderRefund": false
  },
  "M20170802203812091716456": {
    "kdtId": 358764,
    "yzUid": 4693602,
    "orderNo": "M20170802203812091716456",
    "fromSource": 3,
    "orderState": 30,
    "orderType": 1,
    "cashierId": 0,
    "remark": "",
    "buyerMemo": "",
    "reserveOrderId": "",
    "reserveOrderNo": "",
    "billOrderNo": "E20170802203812061000001",
    "billOrderId": "1395956292409884673",
    "finishTime": 0,
    "billTime": 1501677493,
    "reserveTime": 0,
    "guestName": "",
    "guestGender": 0,
    "createTime": 1501677493,
    "updateTime": 1501677493,
    "billOrderPaid": false,
    "billOrderRefund": false
  },
  "M20170802191720047017971": {
    "kdtId": 358764,
    "yzUid": 4693602,
    "orderNo": "M20170802191720047017971",
    "fromSource": 3,
    "orderState": 30,
    "orderType": 1,
    "cashierId": 0,
    "remark": "",
    "buyerMemo": "",
    "reserveOrderId": "",
    "reserveOrderNo": "",
    "billOrderNo": "E20170802191720061000001",
    "billOrderId": "1395945872819224577",
    "finishTime": 0,
    "billTime": 1501672640,
    "reserveTime": 0,
    "guestName": "",
    "guestGender": 0,
    "createTime": 1501672640,
    "updateTime": 1501672640,
    "billOrderPaid": false,
    "billOrderRefund": false
  },
  "M20170802191331066116612": {
    "kdtId": 358764,
    "yzUid": 4693602,
    "orderNo": "M20170802191331066116612",
    "fromSource": 3,
    "orderState": 30,
    "orderType": 1,
    "cashierId": 0,
    "remark": "",
    "buyerMemo": "",
    "reserveOrderId": "",
    "reserveOrderNo": "",
    "billOrderNo": "E20170802191331061000001",
    "billOrderId": "1395945381045469185",
    "finishTime": 0,
    "billTime": 1501672411,
    "reserveTime": 0,
    "guestName": "",
    "guestGender": 0,
    "createTime": 1501672411,
    "updateTime": 1501672411,
    "billOrderPaid": false,
    "billOrderRefund": false
  },
  "M20170802202938096965091": {
    "kdtId": 358764,
    "yzUid": 4693602,
    "orderNo": "M20170802202938096965091",
    "fromSource": 3,
    "orderState": 30,
    "orderType": 1,
    "cashierId": 0,
    "remark": "",
    "buyerMemo": "",
    "reserveOrderId": "",
    "reserveOrderNo": "",
    "billOrderNo": "E20170802202939061000001",
    "billOrderId": "1395955190750773249",
    "finishTime": 0,
    "billTime": 1501676979,
    "reserveTime": 0,
    "guestName": "",
    "guestGender": 0,
    "createTime": 1501676979,
    "updateTime": 1501676979,
    "billOrderPaid": false,
    "billOrderRefund": false
  },
  "M20170802203103012834642": {
    "kdtId": 358764,
    "yzUid": 4693602,
    "orderNo": "M20170802203103012834642",
    "fromSource": 3,
    "orderState": 30,
    "orderType": 1,
    "cashierId": 0,
    "remark": "",
    "buyerMemo": "",
    "reserveOrderId": "",
    "reserveOrderNo": "",
    "billOrderNo": "E20170802203103061000001",
    "billOrderId": "1395955371139399681",
    "finishTime": 0,
    "billTime": 1501677063,
    "reserveTime": 0,
    "guestName": "",
    "guestGender": 0,
    "createTime": 1501677063,
    "updateTime": 1501677063,
    "billOrderPaid": false,
    "billOrderRefund": false
  },
  "M20170802203521063948384": {
    "kdtId": 358764,
    "yzUid": 4693602,
    "orderNo": "M20170802203521063948384",
    "fromSource": 3,
    "orderState": 30,
    "orderType": 1,
    "cashierId": 0,
    "remark": "",
    "buyerMemo": "",
    "reserveOrderId": "",
    "reserveOrderNo": "",
    "billOrderNo": "E20170802203521061000001",
    "billOrderId": "1395955925190180865",
    "finishTime": 0,
    "billTime": 1501677321,
    "reserveTime": 0,
    "guestName": "",
    "guestGender": 0,
    "createTime": 1501677321,
    "updateTime": 1501677321,
    "billOrderPaid": false,
    "billOrderRefund": false
  },
  "M20170802203509075220670": {
    "kdtId": 358764,
    "yzUid": 4693602,
    "orderNo": "M20170802203509075220670",
    "fromSource": 3,
    "orderState": 30,
    "orderType": 1,
    "cashierId": 0,
    "remark": "",
    "buyerMemo": "",
    "reserveOrderId": "",
    "reserveOrderNo": "",
    "billOrderNo": "E20170802203509061000001",
    "billOrderId": "1395955899420377089",
    "finishTime": 0,
    "billTime": 1501677309,
    "reserveTime": 0,
    "guestName": "",
    "guestGender": 0,
    "createTime": 1501677309,
    "updateTime": 1501677309,
    "billOrderPaid": false,
    "billOrderRefund": false
  },
  "M20170711012132003193336": {
    "kdtId": 358764,
    "yzUid": 4716328,
    "orderNo": "M20170711012132003193336",
    "fromSource": 3,
    "orderState": 30,
    "orderType": 1,
    "cashierId": 4693602,
    "remark": "",
    "buyerMemo": "",
    "reserveOrderId": "",
    "reserveOrderNo": "",
    "billOrderNo": "E20170711012132080800001",
    "billOrderId": "1391725320230404097",
    "finishTime": 0,
    "billTime": 1499707292,
    "reserveTime": 0,
    "guestName": "",
    "guestGender": 0,
    "createTime": 1499707292,
    "updateTime": 1499707292,
    "billOrderPaid": false,
    "billOrderRefund": false
  },
  "M20170802201014058317905": {
    "kdtId": 358764,
    "yzUid": 4693602,
    "orderNo": "M20170802201014058317905",
    "fromSource": 3,
    "orderState": 30,
    "orderType": 1,
    "cashierId": 0,
    "remark": "",
    "buyerMemo": "",
    "reserveOrderId": "",
    "reserveOrderNo": "",
    "billOrderNo": "E20170802201014061000001",
    "billOrderId": "1395952688932323329",
    "finishTime": 0,
    "billTime": 1501675814,
    "reserveTime": 0,
    "guestName": "",
    "guestGender": 0,
    "createTime": 1501675814,
    "updateTime": 1501675814,
    "billOrderPaid": false,
    "billOrderRefund": false
  },
  "M20170802192748012323336": {
    "kdtId": 358764,
    "yzUid": 4693602,
    "orderNo": "M20170802192748012323336",
    "fromSource": 3,
    "orderState": 30,
    "orderType": 1,
    "cashierId": 0,
    "remark": "",
    "buyerMemo": "",
    "reserveOrderId": "",
    "reserveOrderNo": "",
    "billOrderNo": "E20170802192748061000001",
    "billOrderId": "1395947221438955521",
    "finishTime": 0,
    "billTime": 1501673268,
    "reserveTime": 0,
    "guestName": "",
    "guestGender": 0,
    "createTime": 1501673268,
    "updateTime": 1501673268,
    "billOrderPaid": false,
    "billOrderRefund": false
  },
  "M20170710112059040893808": {
    "kdtId": 358764,
    "yzUid": 4716328,
    "orderNo": "M20170710112059040893808",
    "fromSource": 3,
    "orderState": 40,
    "orderType": 1,
    "cashierId": 0,
    "remark": "",
    "buyerMemo": "",
    "reserveOrderId": "",
    "reserveOrderNo": "",
    "billOrderNo": "E20170710112059080800001",
    "billOrderId": "1391617016187584513",
    "finishTime": 1499656862,
    "billTime": 1499656859,
    "reserveTime": 0,
    "guestName": "",
    "guestGender": 0,
    "createTime": 1499656859,
    "updateTime": 1499656862,
    "billOrderPaid": true,
    "billOrderRefund": false
  },
  "M20170802191436024048062": {
    "kdtId": 358764,
    "yzUid": 4693602,
    "orderNo": "M20170802191436024048062",
    "fromSource": 3,
    "orderState": 30,
    "orderType": 1,
    "cashierId": 0,
    "remark": "",
    "buyerMemo": "",
    "reserveOrderId": "",
    "reserveOrderNo": "",
    "billOrderNo": "E20170802191436061000001",
    "billOrderId": "1395945520631906305",
    "finishTime": 0,
    "billTime": 1501672476,
    "reserveTime": 0,
    "guestName": "",
    "guestGender": 0,
    "createTime": 1501672476,
    "updateTime": 1501672476,
    "billOrderPaid": false,
    "billOrderRefund": false
  },
  "M20170711012052063860496": {
    "kdtId": 358764,
    "yzUid": 4716328,
    "orderNo": "M20170711012052063860496",
    "fromSource": 3,
    "orderState": 30,
    "orderType": 1,
    "cashierId": 4693602,
    "remark": "",
    "buyerMemo": "",
    "reserveOrderId": "",
    "reserveOrderNo": "",
    "billOrderNo": "E20170711012052080800001",
    "billOrderId": "1391725234331058177",
    "finishTime": 0,
    "billTime": 1499707252,
    "reserveTime": 0,
    "guestName": "",
    "guestGender": 0,
    "createTime": 1499707252,
    "updateTime": 1499707252,
    "billOrderPaid": false,
    "billOrderRefund": false
  },
  "M20170802201535094086424": {
    "kdtId": 358764,
    "yzUid": 4693602,
    "orderNo": "M20170802201535094086424",
    "fromSource": 3,
    "orderState": 30,
    "orderType": 1,
    "cashierId": 0,
    "remark": "",
    "buyerMemo": "",
    "reserveOrderId": "",
    "reserveOrderNo": "",
    "billOrderNo": "E20170802201536061000001",
    "billOrderId": "1395953380422057985",
    "finishTime": 0,
    "billTime": 1501676136,
    "reserveTime": 0,
    "guestName": "",
    "guestGender": 0,
    "createTime": 1501676136,
    "updateTime": 1501676136,
    "billOrderPaid": false,
    "billOrderRefund": false
  },
  "M20170802201331057220466": {
    "kdtId": 358764,
    "yzUid": 4693602,
    "orderNo": "M20170802201331057220466",
    "fromSource": 3,
    "orderState": 30,
    "orderType": 1,
    "cashierId": 0,
    "remark": "",
    "buyerMemo": "",
    "reserveOrderId": "",
    "reserveOrderNo": "",
    "billOrderNo": "E20170802201331061000001",
    "billOrderId": "1395953111986601985",
    "finishTime": 0,
    "billTime": 1501676011,
    "reserveTime": 0,
    "guestName": "",
    "guestGender": 0,
    "createTime": 1501676011,
    "updateTime": 1501676011,
    "billOrderPaid": false,
    "billOrderRefund": false
  },
  "M20170711011929054130614": {
    "kdtId": 358764,
    "yzUid": 4716328,
    "orderNo": "M20170711011929054130614",
    "fromSource": 3,
    "orderState": 30,
    "orderType": 1,
    "cashierId": 4693602,
    "remark": "",
    "buyerMemo": "",
    "reserveOrderId": "",
    "reserveOrderNo": "",
    "billOrderNo": "E20170711011929080800001",
    "billOrderId": "1391725056089915393",
    "finishTime": 0,
    "billTime": 1499707169,
    "reserveTime": 0,
    "guestName": "",
    "guestGender": 0,
    "createTime": 1499707169,
    "updateTime": 1499707169,
    "billOrderPaid": false,
    "billOrderRefund": false
  },
  "M20170802201435052118054": {
    "kdtId": 358764,
    "yzUid": 4693602,
    "orderNo": "M20170802201435052118054",
    "fromSource": 3,
    "orderState": 30,
    "orderType": 1,
    "cashierId": 0,
    "remark": "",
    "buyerMemo": "",
    "reserveOrderId": "",
    "reserveOrderNo": "",
    "billOrderNo": "E20170802201435061000001",
    "billOrderId": "1395953249425555457",
    "finishTime": 0,
    "billTime": 1501676075,
    "reserveTime": 0,
    "guestName": "",
    "guestGender": 0,
    "createTime": 1501676075,
    "updateTime": 1501676075,
    "billOrderPaid": false,
    "billOrderRefund": false
  },
  "M20170802202640037641028": {
    "kdtId": 358764,
    "yzUid": 4693602,
    "orderNo": "M20170802202640037641028",
    "fromSource": 3,
    "orderState": 30,
    "orderType": 1,
    "cashierId": 0,
    "remark": "",
    "buyerMemo": "",
    "reserveOrderId": "",
    "reserveOrderNo": "",
    "billOrderNo": "E20170802202640061000001",
    "billOrderId": "1395954806351200257",
    "finishTime": 0,
    "billTime": 1501676800,
    "reserveTime": 0,
    "guestName": "",
    "guestGender": 0,
    "createTime": 1501676800,
    "updateTime": 1501676800,
    "billOrderPaid": false,
    "billOrderRefund": false
  },
  "M20170711012711033921911": {
    "kdtId": 358764,
    "yzUid": 4716328,
    "orderNo": "M20170711012711033921911",
    "fromSource": 3,
    "orderState": 30,
    "orderType": 1,
    "cashierId": 4693602,
    "remark": "",
    "buyerMemo": "",
    "reserveOrderId": "",
    "reserveOrderNo": "",
    "billOrderNo": "E20170711012711080800001",
    "billOrderId": "1391726048227360769",
    "finishTime": 0,
    "billTime": 1499707631,
    "reserveTime": 0,
    "guestName": "",
    "guestGender": 0,
    "createTime": 1499707631,
    "updateTime": 1499707631,
    "billOrderPaid": false,
    "billOrderRefund": false
  },
  "M20170711014038045380596": {
    "kdtId": 358764,
    "yzUid": 4716328,
    "orderNo": "M20170711014038045380596",
    "fromSource": 3,
    "orderState": 30,
    "orderType": 1,
    "cashierId": 4693602,
    "remark": "",
    "buyerMemo": "",
    "reserveOrderId": "",
    "reserveOrderNo": "",
    "billOrderNo": "E20170711014038080800001",
    "billOrderId": "1391727781246664705",
    "finishTime": 0,
    "billTime": 1499708438,
    "reserveTime": 0,
    "guestName": "",
    "guestGender": 0,
    "createTime": 1499708438,
    "updateTime": 1499708438,
    "billOrderPaid": false,
    "billOrderRefund": false
  },
  "M20170710105239070535571": {
    "kdtId": 358764,
    "yzUid": 4693602,
    "orderNo": "M20170710105239070535571",
    "fromSource": 3,
    "orderState": 30,
    "orderType": 1,
    "cashierId": 4693602,
    "remark": "",
    "buyerMemo": "",
    "reserveOrderId": "",
    "reserveOrderNo": "",
    "billOrderNo": "E20170710105239061000001",
    "billOrderId": "1391613365361573889",
    "finishTime": 0,
    "billTime": 1499655160,
    "reserveTime": 0,
    "guestName": "",
    "guestGender": 0,
    "createTime": 1499655160,
    "updateTime": 1499655160,
    "billOrderPaid": false,
    "billOrderRefund": false
  },
  "M20170802203022048049130": {
    "kdtId": 358764,
    "yzUid": 4693602,
    "orderNo": "M20170802203022048049130",
    "fromSource": 3,
    "orderState": 30,
    "orderType": 1,
    "cashierId": 0,
    "remark": "",
    "buyerMemo": "",
    "reserveOrderId": "",
    "reserveOrderNo": "",
    "billOrderNo": "E20170802203022061000001",
    "billOrderId": "1395955283092570113",
    "finishTime": 0,
    "billTime": 1501677022,
    "reserveTime": 0,
    "guestName": "",
    "guestGender": 0,
    "createTime": 1501677022,
    "updateTime": 1501677022,
    "billOrderPaid": false,
    "billOrderRefund": false
  },
  "M20170710105322061278282": {
    "kdtId": 358764,
    "yzUid": 4693602,
    "orderNo": "M20170710105322061278282",
    "fromSource": 3,
    "orderState": 30,
    "orderType": 1,
    "cashierId": 4693602,
    "remark": "",
    "buyerMemo": "",
    "reserveOrderId": "",
    "reserveOrderNo": "",
    "billOrderNo": "E20170710105322061000001",
    "billOrderId": "1391613457703370753",
    "finishTime": 0,
    "billTime": 1499655203,
    "reserveTime": 0,
    "guestName": "",
    "guestGender": 0,
    "createTime": 1499655203,
    "updateTime": 1499655203,
    "billOrderPaid": false,
    "billOrderRefund": false
  },
  "M20170710110236075793278": {
    "kdtId": 358764,
    "yzUid": 4693602,
    "orderNo": "M20170710110236075793278",
    "fromSource": 3,
    "orderState": 30,
    "orderType": 1,
    "cashierId": 4693602,
    "remark": "chagege",
    "buyerMemo": "",
    "reserveOrderId": "",
    "reserveOrderNo": "",
    "billOrderNo": "E20170710110236061000002",
    "billOrderId": "1391614647409312745",
    "finishTime": 0,
    "billTime": 1499655757,
    "reserveTime": 0,
    "guestName": "",
    "guestGender": 0,
    "createTime": 1499655757,
    "updateTime": 1499655757,
    "billOrderPaid": false,
    "billOrderRefund": false
  },
  "M20170802201157091257883": {
    "kdtId": 358764,
    "yzUid": 4693602,
    "orderNo": "M20170802201157091257883",
    "fromSource": 3,
    "orderState": 30,
    "orderType": 1,
    "cashierId": 0,
    "remark": "",
    "buyerMemo": "",
    "reserveOrderId": "",
    "reserveOrderNo": "",
    "billOrderNo": "E20170802201158061000001",
    "billOrderId": "1395952912270622721",
    "finishTime": 0,
    "billTime": 1501675918,
    "reserveTime": 0,
    "guestName": "",
    "guestGender": 0,
    "createTime": 1501675918,
    "updateTime": 1501675918,
    "billOrderPaid": false,
    "billOrderRefund": false
  },
  "M20170710123816076425082": {
    "kdtId": 358764,
    "yzUid": 4693602,
    "orderNo": "M20170710123816076425082",
    "fromSource": 3,
    "orderState": 30,
    "orderType": 1,
    "cashierId": 4693602,
    "remark": "",
    "buyerMemo": "",
    "reserveOrderId": "",
    "reserveOrderNo": "",
    "billOrderNo": "E20170710123816061000001",
    "billOrderId": "1391626973965451265",
    "finishTime": 0,
    "billTime": 1499661497,
    "reserveTime": 0,
    "guestName": "",
    "guestGender": 0,
    "createTime": 1499661497,
    "updateTime": 1499661497,
    "billOrderPaid": false,
    "billOrderRefund": false
  },
  "M20170802201659044728065": {
    "kdtId": 358764,
    "yzUid": 4693602,
    "orderNo": "M20170802201659044728065",
    "fromSource": 3,
    "orderState": 30,
    "orderType": 1,
    "cashierId": 0,
    "remark": "",
    "buyerMemo": "",
    "reserveOrderId": "",
    "reserveOrderNo": "",
    "billOrderNo": "E20170802201659061000001",
    "billOrderId": "1395953558663200769",
    "finishTime": 0,
    "billTime": 1501676219,
    "reserveTime": 0,
    "guestName": "",
    "guestGender": 0,
    "createTime": 1501676219,
    "updateTime": 1501676219,
    "billOrderPaid": false,
    "billOrderRefund": false
  },
  "M20170710111254055355719": {
    "kdtId": 358764,
    "yzUid": 5182819,
    "orderNo": "M20170710111254055355719",
    "fromSource": 3,
    "orderState": 40,
    "orderType": 1,
    "cashierId": 0,
    "remark": "",
    "buyerMemo": "",
    "reserveOrderId": "",
    "reserveOrderNo": "",
    "billOrderNo": "E20170710111254035500001",
    "billOrderId": "1391615974420512769",
    "finishTime": 1499656376,
    "billTime": 1499656374,
    "reserveTime": 0,
    "guestName": "",
    "guestGender": 0,
    "createTime": 1499656374,
    "updateTime": 1499656376,
    "billOrderPaid": true,
    "billOrderRefund": false
  },
  "M20170802191303016038602": {
    "kdtId": 358764,
    "yzUid": 4693602,
    "orderNo": "M20170802191303016038602",
    "fromSource": 3,
    "orderState": 30,
    "orderType": 1,
    "cashierId": 0,
    "remark": "",
    "buyerMemo": "",
    "reserveOrderId": "",
    "reserveOrderNo": "",
    "billOrderNo": "E20170802191303061000001",
    "billOrderId": "1395945320915927041",
    "finishTime": 0,
    "billTime": 1501672383,
    "reserveTime": 0,
    "guestName": "",
    "guestGender": 0,
    "createTime": 1501672383,
    "updateTime": 1501672383,
    "billOrderPaid": false,
    "billOrderRefund": false
  },
  "M20170802203726053699728": {
    "kdtId": 358764,
    "yzUid": 4693602,
    "orderNo": "M20170802203726053699728",
    "fromSource": 3,
    "orderState": 30,
    "orderType": 1,
    "cashierId": 0,
    "remark": "",
    "buyerMemo": "",
    "reserveOrderId": "",
    "reserveOrderNo": "",
    "billOrderNo": "E20170802203726061000001",
    "billOrderId": "1395956193625636865",
    "finishTime": 0,
    "billTime": 1501677446,
    "reserveTime": 0,
    "guestName": "",
    "guestGender": 0,
    "createTime": 1501677446,
    "updateTime": 1501677446,
    "billOrderPaid": false,
    "billOrderRefund": false
  },
  "M20170802201844039513430": {
    "kdtId": 358764,
    "yzUid": 4693602,
    "orderNo": "M20170802201844039513430",
    "fromSource": 3,
    "orderState": 30,
    "orderType": 1,
    "cashierId": 0,
    "remark": "",
    "buyerMemo": "",
    "reserveOrderId": "",
    "reserveOrderNo": "",
    "billOrderNo": "E20170802201844061000001",
    "billOrderId": "1395953784148983809",
    "finishTime": 0,
    "billTime": 1501676324,
    "reserveTime": 0,
    "guestName": "",
    "guestGender": 0,
    "createTime": 1501676324,
    "updateTime": 1501676324,
    "billOrderPaid": false,
    "billOrderRefund": false
  },
  "M20170802203633022833864": {
    "kdtId": 358764,
    "yzUid": 4693602,
    "orderNo": "M20170802203633022833864",
    "fromSource": 3,
    "orderState": 30,
    "orderType": 1,
    "cashierId": 0,
    "remark": "",
    "buyerMemo": "",
    "reserveOrderId": "",
    "reserveOrderNo": "",
    "billOrderNo": "E20170802203633061000001",
    "billOrderId": "1395956079809003521",
    "finishTime": 0,
    "billTime": 1501677393,
    "reserveTime": 0,
    "guestName": "",
    "guestGender": 0,
    "createTime": 1501677393,
    "updateTime": 1501677393,
    "billOrderPaid": false,
    "billOrderRefund": false
  },
  "M20170802200843056889973": {
    "kdtId": 358764,
    "yzUid": 4693602,
    "orderNo": "M20170802200843056889973",
    "fromSource": 3,
    "orderState": 30,
    "orderType": 1,
    "cashierId": 0,
    "remark": "",
    "buyerMemo": "",
    "reserveOrderId": "",
    "reserveOrderNo": "",
    "billOrderNo": "E20170802200843061000001",
    "billOrderId": "1395952493511311361",
    "finishTime": 0,
    "billTime": 1501675723,
    "reserveTime": 0,
    "guestName": "",
    "guestGender": 0,
    "createTime": 1501675723,
    "updateTime": 1501675723,
    "billOrderPaid": false,
    "billOrderRefund": false
  }
}
